<?xml version="1.0" encoding="utf-8"?>
<!--
    Copyright 2019 Bootleggers ROM
    Licensed under the Apache License, Version 2.0 (the "License");
    you may not use this file except in compliance with the License.
    You may obtain a copy of the License at
        http://www.apache.org/licenses/LICENSE-2.0
    Unless required by applicable law or agreed to in writing, software
    distributed under the License is distributed on an "AS IS" BASIS,
    WITHOUT WARRANTIES OR CONDITIONS OF ANY KIND, either express or implied.
    See the License for the specific language governing permissions and
    limitations under the License.
-->
<fonts-modification version="1">
    <family customizationType="new-named-family" name="gobold-sys">
        <font weight="300" style="normal">GoboldThinLight.ttf</font>
        <font weight="300" style="italic">GoboldThinLight-Italic.ttf</font>
        <font weight="400" style="normal">Gobold.ttf</font>
        <font weight="400" style="italic">Gobold-Italic.ttf</font>
        <font weight="700" style="normal">GoboldBold.ttf</font>
        <font weight="700" style="italic">GoboldBold-Italic.ttf</font>
    </family>

    <alias name="gobold-light-sys" to="gobold-sys" weight="300" />

    <!-- Lockscren Fonts -->
    <family customizationType="new-named-family" name="roadrage-sys">
        <font weight="300" style="normal">RoadRage-Regular.ttf</font>
    </family>
    <family customizationType="new-named-family" name="snowstorm-sys">
        <font weight="300" style="normal">Snowstorm-Regular.ttf</font>
    </family>
    <family customizationType="new-named-family" name="googlesans-sys">
        <font weight="300" style="normal">GoogleSans-Medium.ttf</font>
    </family>
    <family customizationType="new-named-family" name="themeable-clock">
        <font weight="300" style="normal">ThemeableClock-vcrosd.ttf</font>
    </family>
    <family customizationType="new-named-family" name="themeable-date">
        <font weight="300" style="normal">ThemeableDate-fc.ttf</font>
    </family>
    <family customizationType="new-named-family" name="themeable-owner">
        <font weight="300" style="normal">ThemeableOwner-fc.ttf</font>
    </family>
    <family customizationType="new-named-family" name="adamcg-pro">
        <font weight="300" style="normal">AdamCGPro-Regular.ttf</font>
    </family>
    <family customizationType="new-named-family" name="alexana-neue">
        <font weight="300" style="normal">AlexanaNeue-Regular.ttf</font>
    </family>
    <family customizationType="new-named-family" name="alien-league">
        <font weight="300" style="normal">AlienLeague-Regular.ttf</font>
    </family>
    <family customizationType="new-named-family" name="azedo-light">
        <font weight="300" style="normal">Azedo-Light.ttf</font>
    </family>
    <family customizationType="new-named-family" name="bignoodle-italic">
        <font weight="300" style="normal">BigNoodleTilting-Italic.ttf</font>
    </family>
    <family customizationType="new-named-family" name="bignoodle-regular">
        <font weight="300" style="normal">BigNoodleTilting-Regular.ttf</font>
    </family>
    <family customizationType="new-named-family" name="biko">
        <font weight="300" style="normal">Biko-Regular.ttf</font>
    </family>
    <family customizationType="new-named-family" name="blern">
        <font weight="300" style="normal">Blern-Regular.ttf</font>
    </family>
    <family customizationType="new-named-family" name="cocobiker">
        <font weight="300" style="normal">CoCoBiker-Regular.ttf</font>
    </family>
    <family customizationType="new-named-family" name="fester">
        <font weight="300" style="normal">Fester-Medium.ttf</font>
    </family>
    <family customizationType="new-named-family" name="ginora-sans">
        <font weight="300" style="normal">GinoraSans-Regular.ttf</font>
    </family>
    <family customizationType="new-named-family" name="inkferno">
        <font weight="300" style="normal">Inkferno-Regular.ttf</font>
    </family>
    <family customizationType="new-named-family" name="instruction">
        <font weight="300" style="normal">Instruction-Regular.ttf</font>
    </family>
    <family customizationType="new-named-family" name="jacklane">
        <font weight="300" style="normal">JackLane-Regular.ttf</font>
    </family>
    <family customizationType="new-named-family" name="metropolis1920">
        <font weight="300" style="normal">Metropolis1920-Regular.ttf</font>
    </family>
    <family customizationType="new-named-family" name="monad">
        <font weight="300" style="normal">Monad-Regular.ttf</font>
    </family>
    <family customizationType="new-named-family" name="neonneon">
        <font weight="300" style="normal">Neoneon-Regular.ttf</font>
    </family>
    <family customizationType="new-named-family" name="noir">
        <font weight="300" style="normal">Noir-Regular.ttf</font>
    </family>
    <family customizationType="new-named-family" name="northfont">
        <font weight="300" style="normal">North-Regular.ttf</font>
    </family>
    <family customizationType="new-named-family" name="outrun-future">
        <font weight="300" style="normal">OutrunFuture-Regular.ttf</font>
    </family>
    <family customizationType="new-named-family" name="qontra">
        <font weight="300" style="normal">Qontra-Regular.ttf</font>
    </family>
    <family customizationType="new-named-family" name="riviera">
        <font weight="300" style="normal">Riviera-Regular.ttf</font>
    </family>
    <family customizationType="new-named-family" name="the-outbox">
        <font weight="300" style="normal">TheOutbox-Regular.ttf</font>
    </family>
    <family customizationType="new-named-family" name="unionfont">
        <font weight="300" style="normal">Union-Regular.ttf</font>
    </family>
    <family customizationType="new-named-family" name="abelreg">
        <font weight="300" style="normal">Abel-Regular.ttf</font>
    </family>
    <family customizationType="new-named-family" name="adventpro">
        <font weight="300" style="normal">AdventPro-Regular.ttf</font>
    </family>
    <family customizationType="new-named-family" name="archivonar">
        <font weight="300" style="normal">ArchivoNarrow-Regular.ttf</font>
    </family>
    <family customizationType="new-named-family" name="autourone">
        <font weight="300" style="normal">AutourOne-Regular.ttf</font>
    </family>
    <family customizationType="new-named-family" name="badscript">
        <font weight="300" style="normal">BadScript-Regular.ttf</font>
    </family>
    <family customizationType="new-named-family" name="bariol-reg">
        <font weight="300" style="normal">Bariol-Regular.ttf</font>
    </family>
    <family customizationType="new-named-family" name="cherryswash">
        <font weight="300" style="normal">CherrySwash-Regular.ttf</font>
    </family>
    <family customizationType="new-named-family" name="codystar">
        <font weight="300" style="normal">Codystar.ttf</font>
    </family>
    <family customizationType="new-named-family" name="hanken">
        <font weight="300" style="normal">Hanken-Light.ttf</font>
    </family>
    <family customizationType="new-named-family" name="ibmplex-mono">
        <font weight="300" style="normal">IBMPlexMono.ttf</font>
    </family>
    <family customizationType="new-named-family" name="ibmplex-light">
        <font weight="300" style="normal">IBMPlexMono-Light.ttf</font>
    </family>
    <family customizationType="new-named-family" name="jura-reg">
        <font weight="300" style="normal">Jura-Regular.ttf</font>
    </family>
    <family customizationType="new-named-family" name="kellyslab">
        <font weight="300" style="normal">KellySlab-Regular.ttf</font>
    </family>
    <family customizationType="new-named-family" name="mittelschrift">
        <font weight="300" style="normal">din1451alt.ttf</font>
    </family>
    <family customizationType="new-named-family" name="pompiere">
        <font weight="300" style="normal">Pompiere-Regular.ttf</font>
    </family>
    <family customizationType="new-named-family" name="raleway-light">
        <font weight="300" style="normal">Raleway-Light.ttf</font>
    </family>
    <family customizationType="new-named-family" name="reemkufi">
        <font weight="300" style="normal">ReemKufi-Regular.ttf</font>
    </family>
    <family customizationType="new-named-family" name="satisfy">
        <font weight="300" style="normal">Satisfy-Regular.ttf</font>
    </family>
    <family customizationType="new-named-family" name="seaweedsc">
        <font weight="300" style="normal">SeaweedScript-Regular.ttf</font>
    </family>
    <family customizationType="new-named-family" name="sedgwick-ave">
        <font weight="300" style="normal">SedgwickAveDisplay-Regular.ttf</font>
    </family>
    <family customizationType="new-named-family" name="vibur">
        <font weight="300" style="normal">Vibur.ttf</font>
    </family>
    <family customizationType="new-named-family" name="voltaire">
        <font weight="300" style="normal">Voltaire.ttf</font>
    </family>
</fonts-modification>